rth/__init__.py
rth/version.py
rth/core/__init__.py
rth/core/dispatcher.py
rth/core/errors.py
rth/virtual_building/__init__.py
rth/virtual_building/ants.py
rth/virtual_building/network_creator.py
rth/virtual_building/routing_tables_generator.py
rth/virtual_building/utils.py
rth-1.0.0.data/scripts/runtests
rth-1.0.0.dist-info/LICENSE
rth-1.0.0.dist-info/METADATA
rth-1.0.0.dist-info/WHEEL
rth-1.0.0.dist-info/top_level.txt
rth-1.0.0.dist-info/RECORD
