Metadata-Version: 2.1
Name: rth
Version: 1.0.0
Summary: Generates paths between the subnetworks of a local network and generates routing tables of all the routers of said local network
Home-page: https://github.com/BioTheWolff/RTH
Author: Fabien Z.
Author-email: contact.biowolf@gmx.fr
Maintainer: Fabien Z.
Maintainer-email: contact.biowolf@gmx.fr
License: MIT
Project-URL: Source Code, https://github.com/BioTheWolff/RTH
Project-URL: Bug Tracker, https://github.com/BioTheWolff/RTH/issues
Platform: UNKNOWN
Classifier: Development Status :: 5 - Production/Stable
Classifier: Intended Audience :: Developers
Classifier: Intended Audience :: System Administrators
Classifier: Topic :: Utilities
Classifier: Programming Language :: Python :: 3
Classifier: License :: OSI Approved :: MIT License
Classifier: Operating System :: OS Independent
Requires-Python: >=3.6
Requires-Dist: nettools
